<?xml version="1.0" encoding="utf-8"?>
<!DOCTYPE hibernate-mapping PUBLIC "-//Hibernate/Hibernate Mapping DTD 3.0//EN"
"http://hibernate.sourceforge.net/hibernate-mapping-3.0.dtd">
<!-- Mapping file autogenerated by MyEclipse Persistence Tools -->
<hibernate-mapping>
	<class name="com.youquan.model.Comment" table="comment" catalog="nature">
		<id name="id" type="java.lang.String">
			<column name="ID" />
			<generator class="assigned" />
		</id>
		<property name="content" type="java.lang.String">
			<column name="CONTENT" length="1000">
				<comment>评论内容</comment>
			</column>
		</property>
		<property name="createTime" type="java.sql.Timestamp">
			<column name="CREATE_TIME" length="19">
				<comment>创建时间</comment>
			</column>
		</property>
		<property name="laud" type="java.lang.Integer">
			<column name="LAUD">
				<comment>点赞数</comment>
			</column>
		</property>
		<property name="essayId" type="java.lang.String">
			<column name="ESSAY_ID">
				<comment>所属帖子</comment>
			</column>
		</property>
		<property name="commentId" type="java.lang.String">
			<column name="COMMENT_ID">
				<comment>评论上级ID（为空表示属于帖子）</comment>
			</column>
		</property>
	</class>
</hibernate-mapping>
